z3c.formui-4.1-py3.11-nspkg.pth
z3c/formui/README.txt
z3c/formui/__init__.py
z3c/formui/adding.py
z3c/formui/browser.py
z3c/formui/configure.zcml
z3c/formui/div-form-browser.zcml
z3c/formui/div-form-display.pt
z3c/formui/div-form-layer.zcml
z3c/formui/div-form-macros.zcml
z3c/formui/div-form-templates.zcml
z3c/formui/div-form.css
z3c/formui/div-form.pt
z3c/formui/div-form.zcml
z3c/formui/form.py
z3c/formui/interfaces.py
z3c/formui/layout.py
z3c/formui/subform-layout.pt
z3c/formui/subform.pt
z3c/formui/table-form-browser.zcml
z3c/formui/table-form-display.pt
z3c/formui/table-form-layer.zcml
z3c/formui/table-form-macros.zcml
z3c/formui/table-form-templates.zcml
z3c/formui/table-form.css
z3c/formui/table-form.pt
z3c/formui/table-form.zcml
z3c/formui/tests.py
z3c.formui-4.1.dist-info/LICENSE.txt
z3c.formui-4.1.dist-info/METADATA
z3c.formui-4.1.dist-info/WHEEL
z3c.formui-4.1.dist-info/namespace_packages.txt
z3c.formui-4.1.dist-info/top_level.txt
z3c.formui-4.1.dist-info/RECORD
