Metadata-Version: 2.1
Name: z3c.formui
Version: 4.1
Summary: A set of initial UI components for z3c.form.
Home-page: https://github.com/zopefoundation/z3c.formui
Author: Stephan Richter, Roger Ineichen and the Zope Community
Author-email: zope-dev@zope.dev
License: ZPL 2.1
Keywords: zope3 form widget
Classifier: Development Status :: 5 - Production/Stable
Classifier: Environment :: Web Environment
Classifier: Intended Audience :: Developers
Classifier: License :: OSI Approved :: Zope Public License
Classifier: Programming Language :: Python
Classifier: Programming Language :: Python :: 3
Classifier: Programming Language :: Python :: 3.8
Classifier: Programming Language :: Python :: 3.9
Classifier: Programming Language :: Python :: 3.10
Classifier: Programming Language :: Python :: 3.11
Classifier: Programming Language :: Python :: 3.12
Classifier: Programming Language :: Python :: 3.13
Classifier: Programming Language :: Python :: Implementation :: CPython
Classifier: Natural Language :: English
Classifier: Operating System :: OS Independent
Classifier: Topic :: Internet :: WWW/HTTP
Classifier: Framework :: Zope :: 3
Requires-Python: >=3.8
License-File: LICENSE.txt
Requires-Dist: setuptools
Requires-Dist: z3c.form >=2.2.0
Requires-Dist: z3c.macro
Requires-Dist: z3c.template
Requires-Dist: zope.component
Requires-Dist: zope.publisher
Requires-Dist: zope.viewlet
Provides-Extra: test
Requires-Dist: lxml ; extra == 'test'
Requires-Dist: z3c.form[test] ; extra == 'test'
Requires-Dist: zope.testing ; extra == 'test'
